fastapi_security_telegram_webhook/__init__.py
fastapi_security_telegram_webhook/py.typed
fastapi_security_telegram_webhook/security.py
fastapi_security_telegram_webhook-0.2.0.dist-info/LICENSE
fastapi_security_telegram_webhook-0.2.0.dist-info/WHEEL
fastapi_security_telegram_webhook-0.2.0.dist-info/METADATA
fastapi_security_telegram_webhook-0.2.0.dist-info/RECORD
