Metadata-Version: 2.1
Name: fastapi-security-telegram-webhook
Version: 0.2.0
Summary: 
Home-page: https://github.com/piterpy-meetup/fastapi-security-telegram-webhook
License: MIT
Keywords: fastapi,fastapi security,telegram,telegram webhook,bot webhook
Author: Dima Boger
Author-email: kotvberloge@gmail.com
Requires-Python: >=3.6
Classifier: License :: OSI Approved :: MIT License
Classifier: Programming Language :: Python :: 3
Classifier: Programming Language :: Python :: 3.6
Classifier: Programming Language :: Python :: 3.7
Classifier: Programming Language :: Python :: 3.8
Requires-Dist: fastapi
Project-URL: Repository, https://github.com/piterpy-meetup/fastapi-security-telegram-webhook
